puppeter/__init__.py
puppeter/__main__.py
puppeter/container.py
puppeter/main.py
puppeter/settings.py
puppeter/domain/__init__.py
puppeter/domain/facter.py
puppeter/domain/gateway/__init__.py
puppeter/domain/gateway/answers.py
puppeter/domain/gateway/csr.py
puppeter/domain/gateway/fqdn.py
puppeter/domain/gateway/installer.py
puppeter/domain/gateway/installer.pyi
puppeter/domain/gateway/script.py
puppeter/domain/model/__init__.py
puppeter/domain/model/answers.py
puppeter/domain/model/configurer.py
puppeter/domain/model/csr.py
puppeter/domain/model/fqdn.py
puppeter/domain/model/gemrequirement.py
puppeter/domain/model/installer.py
puppeter/domain/model/javafacts.py
puppeter/domain/model/ordered.py
puppeter/domain/model/osfacts.py
puppeter/domain/model/withoptions.py
puppeter/persistence/__init__.py
puppeter/persistence/gateway/__init__.py
puppeter/persistence/gateway/answers.py
puppeter/persistence/gateway/bash-libraries.sh
puppeter/persistence/gateway/csr.py
puppeter/persistence/gateway/csr_agent.pp
puppeter/persistence/gateway/csr_server.pp
puppeter/persistence/gateway/debian-persist-fqdn.pp
puppeter/persistence/gateway/fqdn.py
puppeter/persistence/gateway/redhat-persist-fqdn.pp
puppeter/persistence/gateway/script.py
puppeter/persistence/gateway/set-fqdn.sh
puppeter/persistence/gateway/installer/__init__.py
puppeter/persistence/gateway/installer/linux.py
puppeter/persistence/gateway/installer/debian/__init__.py
puppeter/persistence/gateway/installer/debian/after4x.py
puppeter/persistence/gateway/installer/debian/apt-update.sh
puppeter/persistence/gateway/installer/debian/base.py
puppeter/persistence/gateway/installer/debian/pc3x-repo.sh
puppeter/persistence/gateway/installer/debian/pc3x.py
puppeter/persistence/gateway/installer/debian/pc4x-repo.sh
puppeter/persistence/gateway/installer/debian/pc4x.py
puppeter/persistence/gateway/installer/debian/pc5x-repo.sh
puppeter/persistence/gateway/installer/debian/pc5x.py
puppeter-0.8.3.dist-info/DESCRIPTION.rst
puppeter-0.8.3.dist-info/METADATA
puppeter-0.8.3.dist-info/RECORD
puppeter-0.8.3.dist-info/WHEEL
puppeter-0.8.3.dist-info/entry_points.txt
puppeter-0.8.3.dist-info/metadata.json
puppeter-0.8.3.dist-info/top_level.txt
