Metadata-Version: 2.0
Name: puppeter
Version: 0.8.3
Summary: Puppeter - an automatic puppet installer
Home-page: https://github.com/coi-gov-pl/puppeter
Author: Center for Information Technology
Author-email: opensource@coi.gov.pl
License: Apache-2.0
Keywords: puppet installation devops unattended
Platform: UNKNOWN
Classifier: Development Status :: 3 - Alpha
Classifier: Intended Audience :: Developers
Classifier: Intended Audience :: System Administrators
Classifier: Environment :: Console
Classifier: Environment :: Console :: Curses
Classifier: Operating System :: POSIX :: Linux
Classifier: Topic :: System :: Installation/Setup
Classifier: License :: OSI Approved :: Apache Software License
Classifier: Programming Language :: Python :: 2
Classifier: Programming Language :: Python :: 2.7
Classifier: Programming Language :: Python :: 3
Classifier: Programming Language :: Python :: 3.3
Classifier: Programming Language :: Python :: 3.4
Classifier: Programming Language :: Python :: 3.5
Classifier: Programming Language :: Python :: 3.6
Requires-Dist: distro
Requires-Dist: enum34
Requires-Dist: ruamel.yaml (<0.15)
Requires-Dist: six
Requires-Dist: typing
Provides-Extra: dev
Requires-Dist: check-manifest; extra == 'dev'
Requires-Dist: setuptools (>=18.5); extra == 'dev'
Provides-Extra: test
Requires-Dist: colorama; extra == 'test'
Requires-Dist: paramiko; extra == 'test'
Requires-Dist: pytest; extra == 'test'
Requires-Dist: pytest-cov; extra == 'test'
Requires-Dist: python-coveralls; extra == 'test'
